netlink.cpython-310-x86_64-linux-gnu.so
netlink_client-1.0.0.dist-info/WHEEL
netlink_client-1.0.0.dist-info/top_level.txt
netlink_client-1.0.0.dist-info/RECORD
netlink_client-1.0.0.dist-info/METADATA
