Metadata-Version: 2.1
Name: netlink-client
Version: 1.0.0
Summary: Python Netlink client for linux
Home-page: https://github.com/BoazTene/netlink
Author: Boaz Tene
Author-email: boaztene2005@gmail.com
License: GNU General Public License
Platform: = Linux
